mphyspy/__init__.py
mphyspy/test.py
mphyspy/cosmology/__init__.py
mphyspy/cosmology/cosmology.py
mphyspy/matrix/__init__.py
mphyspy/matrix/matrix.py
mphyspy/qmechanic/__init__.py
mphyspy/qmechanic/atom.py
mphyspy/qmechanic/molecules.py
mphyspy/qmechanic/nuclear.py
mphyspy/qmechanic/quantum.py
mphyspy/qmechanic/schrodinger.py
mphyspy/srelativity/__init__.py
mphyspy/srelativity/srelativity.py
mphyspy/tool/__init__.py
mphyspy/tool/constants.py
mphyspy/tool/conversion.py
mphyspy/tool/geometry.py
mphyspy-0.2.3.dist-info/LICENSE
mphyspy-0.2.3.dist-info/METADATA
mphyspy-0.2.3.dist-info/WHEEL
mphyspy-0.2.3.dist-info/top_level.txt
mphyspy-0.2.3.dist-info/RECORD
