Metadata-Version: 2.1
Name: mphyspy
Version: 0.2.3
Summary: Python3 library for calculating college-level modern physics
Home-page: https://github.com/eunchan1001/mphyspy.git
Author: Eunchan Cho
Author-email: eunchan1001@gmail.com
License: MIT
Platform: UNKNOWN
Classifier: License :: OSI Approved :: MIT License
Classifier: Operating System :: OS Independent
Classifier: Programming Language :: Python :: 3.7
Requires-Dist: mphyspy
Requires-Dist: mpmath (==1.1.0)
Requires-Dist: numpy (==1.18.2)
Requires-Dist: sympy (==1.5.1)
